struct_types-0.1.0.dist-info/METADATA
struct_types-0.1.0.dist-info/WHEEL
struct_types/__init__.py
struct_types/py.typed
struct_types/struct.py
struct_types/unit.py
struct_types-0.1.0.dist-info/RECORD
