Metadata-Version: 2.1
Name: struct-types
Version: 0.1.0
Summary: Static + runtime class declaration level structural types/interface validation
Author-Email: gekkotadev <114091010+GekkotaDev@users.noreply.github.com>
License: Apache-2.0
Classifier: Development Status :: 3 - Alpha
Classifier: License :: OSI Approved :: Apache Software License
Classifier: Typing :: Typed
Requires-Python: >=3.12
